pypub/__init__.py
pypub/builder.py
pypub/chapter.py
pypub/epub.py
pypub/factory.py
pypub/static/container.xml
pypub/static/mimetype
pypub/static/css/coverpage.css
pypub/static/css/styles.css
pypub/static/fonts/free_mono.ttf
pypub/static/img/cover.png
pypub/templates/book.ncx.j2
pypub/templates/book.opf.j2
pypub/templates/coverpage.xhtml.j2
pypub/templates/page.xhtml.j2
pypub/templates/toc.xhtml.j2
pypub/tests/__init__.py
pypub/tests/__main__.py
pypub/tests/chapter.py
pypub/tests/epub.py
pypub/tests/factory.py
pypub/tests/profile.py
pypub3-2.0.9.dist-info/LICENSE
pypub3-2.0.9.dist-info/METADATA
pypub3-2.0.9.dist-info/WHEEL
pypub3-2.0.9.dist-info/top_level.txt
pypub3-2.0.9.dist-info/RECORD
