Metadata-Version: 2.1
Name: pypub3
Version: 2.0.9
Summary: A python3 library to generate custom epub books.
Author-email: Andrew Scott <imgurbot12@gmail.com>
License: The MIT License (MIT)
Project-URL: Repository, https://github.com/imgurbot12/pypub.git
Keywords: epub,ebook
Classifier: Typing :: Typed
Classifier: License :: OSI Approved :: MIT License
Classifier: Intended Audience :: Developers
Classifier: Operating System :: OS Independent
Classifier: Programming Language :: Python :: 3
Classifier: Programming Language :: Python :: 3 :: Only
Classifier: Programming Language :: Python :: 3.8
Classifier: Programming Language :: Python :: 3.9
Classifier: Programming Language :: Python :: 3.10
Classifier: Programming Language :: Python :: 3.11
Classifier: Programming Language :: Python :: 3.12
Classifier: Programming Language :: Python :: 3.13
Requires-Python: >=3.8
License-File: LICENSE
Requires-Dist: pyxml3>=0.0.2
Requires-Dist: Jinja2>=3.1.6
Requires-Dist: pillow>=10.4.0
Requires-Dist: filetype>=1.2.0
